jsonrpc_ns
