Metadata-Version: 1.0
Name: jsonrpc-ns
Version: 0.4
Summary: Lightweight JSON-RPC 2.0 library for building TCP (Netstring) clients
Home-page: http://github.com/flowroute/jsonrpc-ns
Author: Flowroute
Author-email: UNKNOWN
License: UNKNOWN
Platform: UNKNOWN
